pipd/__init__.py
pipd/pipe.py
pipd/utils.py
pipd/pipes/__init__.py
pipd/pipes/batch.py
pipd/pipes/filter.py
pipd/pipes/filter_cached.py
pipd/pipes/limit.py
pipd/pipes/log.py
pipd/pipes/map.py
pipd/pipes/map_key.py
pipd/pipes/mix.py
pipd/pipes/read_csv.py
pipd/pipes/read_files.py
pipd/pipes/read_lines.py
pipd/pipes/repeat.py
pipd/pipes/shuffle.py
pipd/pipes/side.py
pipd/pipes/sleep.py
pipd/pipes/tqdm.py
pipd/pipes/unbatch.py
pipd/pipes/write_csv.py
pipd/pipes/write_lines.py
pipd/tests/__init__.py
pipd/tests/test_pipe.py
pipd/tests/test_pipes.py
pipd-0.2.2.dist-info/METADATA
pipd-0.2.2.dist-info/WHEEL
pipd-0.2.2.dist-info/top_level.txt
pipd-0.2.2.dist-info/RECORD
