Metadata-Version: 2.1
Name: pipd
Version: 0.2.2
Summary: Utility functions for python data pipelines.
Home-page: https://github.com/elevenlabs/pipd
Author: ElevenLabs
Keywords: data processing,pipeline
